setup.py
moki/__init__.py
moki/compatibility_utils.py
moki/extract.py
moki/kindleunpack.py
moki/mobi_cover.py
moki/mobi_dict.py
moki/mobi_header.py
moki/mobi_html.py
moki/mobi_index.py
moki/mobi_k8proc.py
moki/mobi_k8resc.py
moki/mobi_nav.py
moki/mobi_ncx.py
moki/mobi_opf.py
moki/mobi_pagemap.py
moki/mobi_sectioner.py
moki/mobi_split.py
moki/mobi_uncompress.py
moki/mobi_utils.py
moki/mobiml2xhtml.py
moki/unipath.py
moki/unpack_structure.py
moki.egg-info/PKG-INFO
moki.egg-info/SOURCES.txt
moki.egg-info/dependency_links.txt
moki.egg-info/requires.txt
moki.egg-info/top_level.txt