Metadata-Version: 1.2
Name: moki
Version: 0.0.3
Summary: remove boring print warning of mobi
Home-page: UNKNOWN
Author: bk
Author-email: wowlupin@outlook.com
License: GPL-3.0
Platform: UNKNOWN
Requires-Python: >=3.7
